README.md
setup.py
ancypwn_backend_wsl2.egg-info/PKG-INFO
ancypwn_backend_wsl2.egg-info/SOURCES.txt
ancypwn_backend_wsl2.egg-info/dependency_links.txt
ancypwn_backend_wsl2.egg-info/requires.txt
ancypwn_backend_wsl2.egg-info/top_level.txt
src/__init__.py
src/backend.py