Metadata-Version: 1.0
Name: ancypwn-backend-wsl2
Version: 0.0.1
Summary: ancypwn windows wsl2 backend
Home-page: https://github.com/Escapingbug/ancypwn-backend-wsl2
Author: Anciety
Author-email: anciety@pku.edu.cn
License: UNKNOWN
Platform: UNKNOWN
